[
    {        "id": 1,        "name": "Batman",        "world": "DC Comics"    },
    {        "id": 2,        "name": "Gandalf",        "world": "Lord of the Rings"    },
    {        "id": 3,        "name": "Wyldstyle",        "world": "The LEGO Movie"    },
    {        "id": 4,        "name": "Aquaman",        "world": "DC Comics"    },
    {        "id": 5,        "name": "Bad Cop",        "world": "The LEGO Movie"    },
    {        "id": 6,        "name": "Bane",        "world": "DC Comics"    },
    {        "id": 7,        "name": "Bart Simpson",        "world": "The Simpsons"    },
    {        "id": 8,        "name": "Benny",        "world": "The LEGO Movie"    },
    {        "id": 9,        "name": "Chell",        "world": "Portal 2"    },
    {        "id": 10,        "name": "Cole",        "world": "Ninjago"    },
    {        "id": 11,        "name": "Cragger",        "world": "Legends of Chima"    },
    {        "id": 12,        "name": "Cyborg",        "world": "DC Comics"    },
    {        "id": 13,        "name": "Cyberman",        "world": "Doctor Who"    },
    {        "id": 14,        "name": "Doc Brown",        "world": "Back to the Future"    },
    {        "id": 15,        "name": "The Doctor",        "world": "Doctor Who"    },
    {        "id": 16,        "name": "Emmet",        "world": "The LEGO Movie"    },
    {        "id": 17,        "name": "Eris",        "world": "Legends of Chima"    },
    {        "id": 18,        "name": "Gimli",        "world": "Lord of the Rings"    },
    {        "id": 19,        "name": "Smeagol/Gollum",        "world": "Lord of the Rings"    },
    {        "id": 20,        "name": "Harley Quinn",        "world": "DC Comics"    },
    {        "id": 21,        "name": "Homer Simpson",        "world": "The Simpsons"    },
    {        "id": 22,        "name": "Jay",        "world": "Ninjago"    },
    {        "id": 23,        "name": "Joker",        "world": "DC Comics"    },
    {        "id": 24,        "name": "Kai",        "world": "Ninjago"    },
    {        "id": 25,        "name": "ACU Trooper",        "world": "Jurassic Park"    },
    {        "id": 26,        "name": "Gamer Kid",        "world": "Midway Arcade"    },
    {        "id": 27,        "name": "Krusty the Clown",        "world": "The Simpsons"    },
    {        "id": 28,        "name": "Laval",        "world": "Legends of Chima"    },
    {        "id": 29,        "name": "Legolas",        "world": "Lord of the Rings"    },
    {        "id": 30,        "name": "Lloyd",        "world": "Ninjago"    },
    {        "id": 31,        "name": "Marty McFly",        "world": "Back to the Future"    },
    {        "id": 32,        "name": "Nya",        "world": "Ninjago"    },
    {        "id": 33,        "name": "Owen Grady",        "world": "Jurassic Park"    },
    {        "id": 34,        "name": "Peter Venkman",        "world": "Ghostbusters"    },
    {        "id": 35,        "name": "Slimer",        "world": "Ghostbusters"    },
    {        "id": 36,        "name": "Scooby Doo",        "world": "Scooby-Doo"    },
    {        "id": 37,        "name": "Sensei Wu",        "world": "Ninjago"    },
    {        "id": 38,        "name": "Shaggy",        "world": "Scooby-Doo"    },
    {        "id": 39,        "name": "Stay Puft",        "world": "Ghostbusters"    },
    {        "id": 40,        "name": "Superman",        "world": "DC Comics"    },
    {        "id": 41,        "name": "Unikitty",        "world": "The LEGO Movie"    },
    {        "id": 42,        "name": "Wicked Witch of the West",        "world": "Wizard of OZ"    },
    {        "id": 43,        "name": "Wonder Woman",        "world": "DC Comics"    },
    {        "id": 44,        "name": "Zane",        "world": "Ninjago"    },
    {        "id": 45,        "name": "Green Arrow",        "world": "DC Comics"    },
    {        "id": 46,        "name": "Supergirl",        "world": "DC Comics"    },
    {        "id": 47,        "name": "Abby Yates",        "world": "Ghostbuster 2016"    },
    {        "id": 48,        "name": "Finn the Human",        "world": "Adventure Time"    },
    {        "id": 49,        "name": "Ethan Hunt",        "world": "Mission Impossible"    },
    {        "id": 50,        "name": "Lumpy Space Princess",        "world": "Adventure Time"    },
    {        "id": 51,        "name": "Jake the Dog",        "world": "Adventure Time"    },
    {        "id": 52,        "name": "Harry Potter",        "world": "Harry Potter"    },
    {        "id": 53,        "name": "Lord Voldemort",        "world": "Harry Potter"    },
    {        "id": 54,        "name": "Michael Knight", "world": "Knight Rider"},
    {        "id": 55,        "name": "B.A. Baracus",        "world": "A-Team"    },
    {        "id": 56,        "name": "Newt Scamander",        "world": "Fantastic Beasts"    },
    {        "id": 57,        "name": "Sonic the Hedgehog",        "world": "Sonic"    },
    {        "id": 58,        "name": "Future Update (unreleased)",        "world": "N/A"    },
    {        "id": 59,        "name": "Gizmo",        "world": "Gremlins"    },
    {        "id": 60,        "name": "Stripe",        "world": "Gremlins"    },
    {        "id": 61,        "name": "E.T.",        "world": "E.T."    },
    {        "id": 62,        "name": "Tina Goldstein",        "world": "Fantastic Beasts"    },
    {        "id": 63,        "name": "Marceline the Vampire Queen",        "world": "Adventure Time"    },
    {        "id": 64,        "name": "Batgirl",        "world":"LEGO Batman Movie"},        
    {        "id": 65,        "name": "Robin",         "world":"LEGO Batman Movie"},
    {        "id": 66,        "name": "Sloth", "world":"Goonies" },
    {        "id": 67,        "name": "Hermione Granger", "world":"Harry Potter" },
    {        "id": 68,        "name": "Chase McCain", "world":"LEGO City" },
    {        "id": 69,        "name": "Excalibur Batman","world":"LEGO Batman Movie"},
    {        "id": 70,        "name": "Raven",         "world":"Teen Titans Go"},        
    {        "id": 71,        "name": "Beast Boy",     "world":"Teen Titans Go"},
    {        "id": 72,        "name": "Betelgeuse",  "world":"Beetle Juice"},
    {        "id": 73,        "name": "Lord Vortech (unreleased)",  "world":"Lego Dimensions"},
    {        "id": 74,        "name": "Blossom",        "world":"Power Puff Girls"},        
    {        "id": 75,        "name": "Bubbles",       "world":"Power Puff Girls"},
    {        "id": 76,        "name": "Buttercup",     "world":"Power Puff Girls"},
    {        "id": 77,        "name": "Starfire",     "world":"Teen Titans Go"},
    {        "id": 78,        "name": "World 15 (unreleased)",        "world":"15"},        
    {        "id": 79,        "name": "World 16 (unreleased)",       "world":"16"},
    {        "id": 80,        "name": "World 17 (unreleased)",       "world":"17"},
    {        "id": 81,        "name": "World 18 (unreleased)",       "world":"18"},
    {        "id": 82,        "name": "World 19 (unreleased)",       "world":"19"},
    {        "id": 83,        "name": "World 20 (unreleased)",        "world":"20"},
    {        "id": 768,       "name": "Unknown",      "world":"Unknown"},
    {        "id": 769,       "name": "Supergirl Red Lantern", "world":"DC Comics"},
    {        "id": 770,       "name": "Unknown",      "world":"Unknown"}
]
